morfoAnalyse/__init__.py
morfoAnalyse-2.3.dist-info/LICENSE.txt
morfoAnalyse-2.3.dist-info/METADATA
morfoAnalyse-2.3.dist-info/WHEEL
morfoAnalyse-2.3.dist-info/top_level.txt
morfoAnalyse-2.3.dist-info/RECORD
