Metadata-Version: 2.1
Name: morfoAnalyse
Version: 2.3
Summary: This package is desgined to help researcher to find stem of the word and 
Author: Alisher Ismailov Shakirovich
Author-email: alisherismailov1991@gmail.com
License: MIT
Classifier: Programming Language :: Python :: 3
Classifier: License :: OSI Approved :: MIT License
Classifier: Operating System :: OS Independent
License-File: LICENSE.txt
